{
  "version": 1,
  "name": "GitLab Dark Grey",
  "background": {
    "fg": "#ffffff",
    "bg": "#222222",
    "bold": false,
    "dim": false,
    "underline": false,
    "reverse": false
  },
  "header": {
    "fg": "#ffffff",
    "bg": "#2d2d2d",
    "bold": false,
    "dim": false,
    "underline": false,
    "reverse": false
  },
  "footer": {
    "fg": "#9c9c9c",
    "bg": "#2d2d2d",
    "bold": false,
    "dim": false,
    "underline": false,
    "reverse": false
  },
  "panel": {
    "fg": "#ffffff",
    "bg": "#222222",
    "bold": false,
    "dim": false,
    "underline": false,
    "reverse": false
  },
  "panel_focused": {
    "fg": "#ffffff",
    "bg": "#343434",
    "bold": false,
    "dim": false,
    "underline": false,
    "reverse": false
  },
  "cmdline": {
    "fg": "#9c9c9c",
    "bg": "#222222",
    "bold": false,
    "dim": false,
    "underline": false,
    "reverse": false
  },
  "overlay": {
    "fg": "#ffffff",
    "bg": "#212121",
    "bold": false,
    "dim": false,
    "underline": false,
    "reverse": false
  },
  "divider": {
    "fg": "#666666",
    "bg": "default",
    "bold": false,
    "dim": false,
    "underline": false,
    "reverse": false
  },
  "text": {
    "fg": "#ffffff",
    "bg": "default",
    "bold": false,
    "dim": false,
    "underline": false,
    "reverse": false
  },
  "text_dim": {
    "fg": "#9c9c9c",
    "bg": "default",
    "bold": false,
    "dim": false,
    "underline": false,
    "reverse": false
  },
  "text_faint": {
    "fg": "#7a7a7a",
    "bg": "default",
    "bold": false,
    "dim": false,
    "underline": false,
    "reverse": false
  },
  "text_error": {
    "fg": "#f57f6c",
    "bg": "default",
    "bold": false,
    "dim": false,
    "underline": false,
    "reverse": false
  },
  "text_warn": {
    "fg": "#d99530",
    "bg": "default",
    "bold": false,
    "dim": false,
    "underline": false,
    "reverse": false
  },
  "text_ok": {
    "fg": "#52b87a",
    "bg": "default",
    "bold": false,
    "dim": false,
    "underline": false,
    "reverse": false
  },
  "list_selected": {
    "fg": "#222222",
    "bg": "#ad95e9",
    "bold": false,
    "dim": false,
    "underline": false,
    "reverse": false
  },
  "table_header": {
    "fg": "#9c9c9c",
    "bg": "#292929",
    "bold": false,
    "dim": false,
    "underline": false,
    "reverse": false
  },
  "active": {
    "fg": "#d99530",
    "bg": "default",
    "bold": true,
    "dim": false,
    "underline": false,
    "reverse": false
  },
  "marked": {
    "fg": "#d99530",
    "bg": "default",
    "bold": true,
    "dim": false,
    "underline": false,
    "reverse": false
  },
  "scroll_track": {
    "fg": "#666666",
    "bg": "default",
    "bold": false,
    "dim": false,
    "underline": false,
    "reverse": false
  },
  "scroll_thumb": {
    "fg": "#ffffff",
    "bg": "default",
    "bold": false,
    "dim": false,
    "underline": false,
    "reverse": false
  },
  "syntax_text": {
    "fg": "#ffffff",
    "bg": "default",
    "bold": false,
    "dim": false,
    "underline": false,
    "reverse": false
  },
  "syntax_comment": {
    "fg": "#7a7a7a",
    "bg": "default",
    "bold": false,
    "dim": false,
    "underline": false,
    "reverse": false
  },
  "syntax_key": {
    "fg": "#7fb6ed",
    "bg": "default",
    "bold": false,
    "dim": false,
    "underline": false,
    "reverse": false
  },
  "cmdline_label": {
    "fg": "#9c9c9c",
    "bg": "#222222",
    "bold": false,
    "dim": false,
    "underline": false,
    "reverse": false
  },
  "cmdline_cursor": {
    "fg": "#222222",
    "bg": "#ad95e9",
    "bold": false,
    "dim": false,
    "underline": false,
    "reverse": false
  },
  "cmdline_inactive": {
    "fg": "#9c9c9c",
    "bg": "#222222",
    "bold": false,
    "dim": false,
    "underline": false,
    "reverse": false
  }
}