{
  "version": 1,
  "name": "Kolorit",
  "background": {
    "fg": "#efecec",
    "bg": "#1d1a1e",
    "bold": false,
    "dim": false,
    "underline": false,
    "reverse": false
  },
  "header": {
    "fg": "#efecec",
    "bg": "#282529",
    "bold": false,
    "dim": false,
    "underline": false,
    "reverse": false
  },
  "footer": {
    "fg": "#918e8f",
    "bg": "#282529",
    "bold": false,
    "dim": false,
    "underline": false,
    "reverse": false
  },
  "panel": {
    "fg": "#efecec",
    "bg": "#1d1a1e",
    "bold": false,
    "dim": false,
    "underline": false,
    "reverse": false
  },
  "panel_focused": {
    "fg": "#efecec",
    "bg": "#2f2c30",
    "bold": false,
    "dim": false,
    "underline": false,
    "reverse": false
  },
  "cmdline": {
    "fg": "#918e8f",
    "bg": "#1d1a1e",
    "bold": false,
    "dim": false,
    "underline": false,
    "reverse": false
  },
  "overlay": {
    "fg": "#efecec",
    "bg": "#1c191d",
    "bold": false,
    "dim": false,
    "underline": false,
    "reverse": false
  },
  "divider": {
    "fg": "#504d51",
    "bg": "default",
    "bold": false,
    "dim": false,
    "underline": false,
    "reverse": false
  },
  "text": {
    "fg": "#efecec",
    "bg": "default",
    "bold": false,
    "dim": false,
    "underline": false,
    "reverse": false
  },
  "text_dim": {
    "fg": "#918e8f",
    "bg": "default",
    "bold": false,
    "dim": false,
    "underline": false,
    "reverse": false
  },
  "text_faint": {
    "fg": "#716e70",
    "bg": "default",
    "bold": false,
    "dim": false,
    "underline": false,
    "reverse": false
  },
  "text_error": {
    "fg": "#ff5b82",
    "bg": "default",
    "bold": false,
    "dim": false,
    "underline": false,
    "reverse": false
  },
  "text_warn": {
    "fg": "#e8e562",
    "bg": "default",
    "bold": false,
    "dim": false,
    "underline": false,
    "reverse": false
  },
  "text_ok": {
    "fg": "#47d7a1",
    "bg": "default",
    "bold": false,
    "dim": false,
    "underline": false,
    "reverse": false
  },
  "list_selected": {
    "fg": "#1d1a1e",
    "bg": "#e1925c",
    "bold": false,
    "dim": false,
    "underline": false,
    "reverse": false
  },
  "table_header": {
    "fg": "#918e8f",
    "bg": "#242125",
    "bold": false,
    "dim": false,
    "underline": false,
    "reverse": false
  },
  "active": {
    "fg": "#e8e562",
    "bg": "default",
    "bold": true,
    "dim": false,
    "underline": false,
    "reverse": false
  },
  "marked": {
    "fg": "#e8e562",
    "bg": "default",
    "bold": true,
    "dim": false,
    "underline": false,
    "reverse": false
  },
  "scroll_track": {
    "fg": "#504d51",
    "bg": "default",
    "bold": false,
    "dim": false,
    "underline": false,
    "reverse": false
  },
  "scroll_thumb": {
    "fg": "#efecec",
    "bg": "default",
    "bold": false,
    "dim": false,
    "underline": false,
    "reverse": false
  },
  "syntax_text": {
    "fg": "#efecec",
    "bg": "default",
    "bold": false,
    "dim": false,
    "underline": false,
    "reverse": false
  },
  "syntax_comment": {
    "fg": "#716e70",
    "bg": "default",
    "bold": false,
    "dim": false,
    "underline": false,
    "reverse": false
  },
  "syntax_key": {
    "fg": "#5db4ee",
    "bg": "default",
    "bold": false,
    "dim": false,
    "underline": false,
    "reverse": false
  },
  "cmdline_label": {
    "fg": "#918e8f",
    "bg": "#1d1a1e",
    "bold": false,
    "dim": false,
    "underline": false,
    "reverse": false
  },
  "cmdline_cursor": {
    "fg": "#1d1a1e",
    "bg": "#e1925c",
    "bold": false,
    "dim": false,
    "underline": false,
    "reverse": false
  },
  "cmdline_inactive": {
    "fg": "#918e8f",
    "bg": "#1d1a1e",
    "bold": false,
    "dim": false,
    "underline": false,
    "reverse": false
  }
}