{
  "version": 1,
  "name": "Selenized Light",
  "background": {
    "fg": "#53676d",
    "bg": "#fbf3db",
    "bold": false,
    "dim": false,
    "underline": false,
    "reverse": false
  },
  "header": {
    "fg": "#53676d",
    "bg": "#eee7d0",
    "bold": false,
    "dim": false,
    "underline": false,
    "reverse": false
  },
  "footer": {
    "fg": "#9fa69e",
    "bg": "#eee7d0",
    "bold": false,
    "dim": false,
    "underline": false,
    "reverse": false
  },
  "panel": {
    "fg": "#53676d",
    "bg": "#fbf3db",
    "bold": false,
    "dim": false,
    "underline": false,
    "reverse": false
  },
  "panel_focused": {
    "fg": "#53676d",
    "bg": "#e7e0c9",
    "bold": false,
    "dim": false,
    "underline": false,
    "reverse": false
  },
  "cmdline": {
    "fg": "#9fa69e",
    "bg": "#fbf3db",
    "bold": false,
    "dim": false,
    "underline": false,
    "reverse": false
  },
  "overlay": {
    "fg": "#53676d",
    "bg": "#fbf3dc",
    "bold": false,
    "dim": false,
    "underline": false,
    "reverse": false
  },
  "divider": {
    "fg": "#bbb39c",
    "bg": "default",
    "bold": false,
    "dim": false,
    "underline": false,
    "reverse": false
  },
  "text": {
    "fg": "#53676d",
    "bg": "default",
    "bold": false,
    "dim": false,
    "underline": false,
    "reverse": false
  },
  "text_dim": {
    "fg": "#9fa69e",
    "bg": "default",
    "bold": false,
    "dim": false,
    "underline": false,
    "reverse": false
  },
  "text_faint": {
    "fg": "#b8bbaf",
    "bg": "default",
    "bold": false,
    "dim": false,
    "underline": false,
    "reverse": false
  },
  "text_error": {
    "fg": "#d2212d",
    "bg": "default",
    "bold": false,
    "dim": false,
    "underline": false,
    "reverse": false
  },
  "text_warn": {
    "fg": "#ad8900",
    "bg": "default",
    "bold": false,
    "dim": false,
    "underline": false,
    "reverse": false
  },
  "text_ok": {
    "fg": "#489100",
    "bg": "default",
    "bold": false,
    "dim": false,
    "underline": false,
    "reverse": false
  },
  "list_selected": {
    "fg": "#00978a",
    "bg": "#ece3cc",
    "bold": false,
    "dim": false,
    "underline": false,
    "reverse": false
  },
  "table_header": {
    "fg": "#9fa69e",
    "bg": "#f3ecd4",
    "bold": false,
    "dim": false,
    "underline": false,
    "reverse": false
  },
  "active": {
    "fg": "#ad8900",
    "bg": "default",
    "bold": true,
    "dim": false,
    "underline": false,
    "reverse": false
  },
  "marked": {
    "fg": "#ad8900",
    "bg": "default",
    "bold": true,
    "dim": false,
    "underline": false,
    "reverse": false
  },
  "scroll_track": {
    "fg": "#bbb39c",
    "bg": "default",
    "bold": false,
    "dim": false,
    "underline": false,
    "reverse": false
  },
  "scroll_thumb": {
    "fg": "#53676d",
    "bg": "default",
    "bold": false,
    "dim": false,
    "underline": false,
    "reverse": false
  },
  "syntax_text": {
    "fg": "#53676d",
    "bg": "default",
    "bold": false,
    "dim": false,
    "underline": false,
    "reverse": false
  },
  "syntax_comment": {
    "fg": "#b8bbaf",
    "bg": "default",
    "bold": false,
    "dim": false,
    "underline": false,
    "reverse": false
  },
  "syntax_key": {
    "fg": "#0072d4",
    "bg": "default",
    "bold": false,
    "dim": false,
    "underline": false,
    "reverse": false
  },
  "cmdline_label": {
    "fg": "#9fa69e",
    "bg": "#fbf3db",
    "bold": false,
    "dim": false,
    "underline": false,
    "reverse": false
  },
  "cmdline_cursor": {
    "fg": "#00978a",
    "bg": "#ece3cc",
    "bold": false,
    "dim": false,
    "underline": false,
    "reverse": false
  },
  "cmdline_inactive": {
    "fg": "#9fa69e",
    "bg": "#fbf3db",
    "bold": false,
    "dim": false,
    "underline": false,
    "reverse": false
  }
}