{
  "version": 1,
  "name": "Sugarplum",
  "background": {
    "fg": "#db7ddd",
    "bg": "#111147",
    "bold": false,
    "dim": false,
    "underline": false,
    "reverse": false
  },
  "header": {
    "fg": "#db7ddd",
    "bg": "#1d1d50",
    "bold": false,
    "dim": false,
    "underline": false,
    "reverse": false
  },
  "footer": {
    "fg": "#804c9a",
    "bg": "#1d1d50",
    "bold": false,
    "dim": false,
    "underline": false,
    "reverse": false
  },
  "panel": {
    "fg": "#db7ddd",
    "bg": "#111147",
    "bold": false,
    "dim": false,
    "underline": false,
    "reverse": false
  },
  "panel_focused": {
    "fg": "#db7ddd",
    "bg": "#242456",
    "bold": false,
    "dim": false,
    "underline": false,
    "reverse": false
  },
  "cmdline": {
    "fg": "#804c9a",
    "bg": "#111147",
    "bold": false,
    "dim": false,
    "underline": false,
    "reverse": false
  },
  "overlay": {
    "fg": "#db7ddd",
    "bg": "#101044",
    "bold": false,
    "dim": false,
    "underline": false,
    "reverse": false
  },
  "divider": {
    "fg": "#44447a",
    "bg": "default",
    "bold": false,
    "dim": false,
    "underline": false,
    "reverse": false
  },
  "text": {
    "fg": "#db7ddd",
    "bg": "default",
    "bold": false,
    "dim": false,
    "underline": false,
    "reverse": false
  },
  "text_dim": {
    "fg": "#804c9a",
    "bg": "default",
    "bold": false,
    "dim": false,
    "underline": false,
    "reverse": false
  },
  "text_faint": {
    "fg": "#623c83",
    "bg": "default",
    "bold": false,
    "dim": false,
    "underline": false,
    "reverse": false
  },
  "text_error": {
    "fg": "#5ca8dc",
    "bg": "default",
    "bold": false,
    "dim": false,
    "underline": false,
    "reverse": false
  },
  "text_warn": {
    "fg": "#249a84",
    "bg": "default",
    "bold": false,
    "dim": false,
    "underline": false,
    "reverse": false
  },
  "text_ok": {
    "fg": "#53b397",
    "bg": "default",
    "bold": false,
    "dim": false,
    "underline": false,
    "reverse": false
  },
  "list_selected": {
    "fg": "#ead8ff",
    "bg": "#5ca8dc",
    "bold": false,
    "dim": false,
    "underline": false,
    "reverse": false
  },
  "table_header": {
    "fg": "#804c9a",
    "bg": "#18184d",
    "bold": false,
    "dim": false,
    "underline": false,
    "reverse": false
  },
  "active": {
    "fg": "#249a84",
    "bg": "default",
    "bold": true,
    "dim": false,
    "underline": false,
    "reverse": false
  },
  "marked": {
    "fg": "#249a84",
    "bg": "default",
    "bold": true,
    "dim": false,
    "underline": false,
    "reverse": false
  },
  "scroll_track": {
    "fg": "#44447a",
    "bg": "default",
    "bold": false,
    "dim": false,
    "underline": false,
    "reverse": false
  },
  "scroll_thumb": {
    "fg": "#db7ddd",
    "bg": "default",
    "bold": false,
    "dim": false,
    "underline": false,
    "reverse": false
  },
  "syntax_text": {
    "fg": "#db7ddd",
    "bg": "default",
    "bold": false,
    "dim": false,
    "underline": false,
    "reverse": false
  },
  "syntax_comment": {
    "fg": "#623c83",
    "bg": "default",
    "bold": false,
    "dim": false,
    "underline": false,
    "reverse": false
  },
  "syntax_key": {
    "fg": "#db7ddd",
    "bg": "default",
    "bold": false,
    "dim": false,
    "underline": false,
    "reverse": false
  },
  "cmdline_label": {
    "fg": "#804c9a",
    "bg": "#111147",
    "bold": false,
    "dim": false,
    "underline": false,
    "reverse": false
  },
  "cmdline_cursor": {
    "fg": "#ead8ff",
    "bg": "#5ca8dc",
    "bold": false,
    "dim": false,
    "underline": false,
    "reverse": false
  },
  "cmdline_inactive": {
    "fg": "#804c9a",
    "bg": "#111147",
    "bold": false,
    "dim": false,
    "underline": false,
    "reverse": false
  }
}